gelatin_extract/__init__.py
gelatin_extract/base/__init__.py
gelatin_extract/base/deserializer.py
gelatin_extract/base/fields.py
gelatin_extract/base/schema.py
gelatin_extract/io/__init__.py
gelatin_extract/io/iterparse.py
gelatin_extract/json/__init__.py
gelatin_extract/json/schema/__init__.py
gelatin_extract/json/schema/fields.py
gelatin_extract/json/schema/key.py
gelatin_extract/json/schema/schema.py
gelatin_extract/json/schema/test_schema.py
gelatin_extract/util.py
gelatin_extract/xml/__init__.py
gelatin_extract/xml/io/__init__.py
gelatin_extract/xml/io/aps.py
gelatin_extract/xml/io/autodetect.py
gelatin_extract/xml/io/iterparse.py
gelatin_extract/xml/io/process.py
gelatin_extract/xml/io/sample.py
gelatin_extract/xml/schema/__init__.py
gelatin_extract/xml/schema/fields.py
gelatin_extract/xml/schema/key.py
gelatin_extract/xml/schema/schema.py
gelatin_extract/xml/schema/test_schema.py
gelatin_extract-0.1.2.dist-info/WHEEL
gelatin_extract-0.1.2.dist-info/METADATA
gelatin_extract-0.1.2.dist-info/RECORD
