Metadata-Version: 2.1
Name: gelatin-extract
Version: 0.1.2
Summary: lightweigh, simple, and fast declarative XML and JSON deserialization
Home-page: https://github.com/parkerhancock/gelatin_extract
License: Apache Software License 2.0
Keywords: deserialization,xml,json,deserialize
Author: Parker Hancock
Author-email: 633163+parkerhancock@users.noreply.github.com
Requires-Python: >=3.9,<4.0
Classifier: Development Status :: 3 - Alpha
Classifier: License :: Other/Proprietary License
Classifier: Programming Language :: Python :: 3
Classifier: Programming Language :: Python :: 3.9
Classifier: Topic :: Text Processing :: Markup :: XML
Requires-Dist: lxml (>=4.8.0,<5.0.0)
Requires-Dist: python-dateutil (>=2.8.2,<3.0.0)
Project-URL: Repository, https://github.com/parkerhancock/gelatin_extract
